skinnywms/__init__.py
skinnywms/datatypes.py
skinnywms/errors.py
skinnywms/protocol.py
skinnywms/server.py
skinnywms/skinny.py
skinnywms/wmssvr.py
skinnywms/data/__init__.py
skinnywms/data/fs.py
skinnywms/data/mvfs.py
skinnywms/fields/GRIBField.py
skinnywms/fields/GeoJSONField.py
skinnywms/fields/NetCDFField.py
skinnywms/fields/__init__.py
skinnywms/grib_bindings/GribField.py
skinnywms/grib_bindings/GribFile.py
skinnywms/grib_bindings/__init__.py
skinnywms/grib_bindings/bindings.py
skinnywms/plot/__init__.py
skinnywms/plot/magics.py
skinnywms/templates/getcapabilities_1.1.1.xml
skinnywms/templates/getcapabilities_1.3.0.xml
skinnywms/templates/leaflet_demo.html
skinnywms/templates/obs.template
skinnywms/templates/present_weather.template
skinnywms/testdata/mosmix.geojson
skinnywms/testdata/mslp.nc
skinnywms/testdata/tp.grib
skinnywms/testdata/tuv.grib
skinnywms-0.11.0.dist-info/licenses/LICENSE.txt
skinnywms-0.11.0.dist-info/METADATA
skinnywms-0.11.0.dist-info/WHEEL
skinnywms-0.11.0.dist-info/entry_points.txt
skinnywms-0.11.0.dist-info/top_level.txt
skinnywms-0.11.0.dist-info/zip-safe
skinnywms-0.11.0.dist-info/RECORD
