Metadata-Version: 2.4
Name: skinnywms
Version: 0.11.0
Summary: A light WMS server to visualise your NetCDF and GRIB data
Home-page: https://github.com/ecmwf/skinnywms
Author: European Centre for Medium-Range Weather Forecasts (ECMWF)
Author-email: software.support@ecmwf.int
License: Apache License Version 2.0
Keywords: magics grib WMS visualisation NetCDF climate meteorology
Classifier: Development Status :: 3 - Alpha
Classifier: Intended Audience :: Developers
Classifier: License :: OSI Approved :: Apache Software License
Classifier: Programming Language :: Python :: 3
Classifier: Programming Language :: Python :: 3.5
Classifier: Programming Language :: Python :: 3.6
Classifier: Programming Language :: Python :: 3.7
Classifier: Programming Language :: Python :: 3.8
Classifier: Programming Language :: Python :: 3.9
Classifier: Programming Language :: Python :: 3.10
Classifier: Programming Language :: Python :: 3.11
Classifier: Programming Language :: Python :: Implementation :: CPython
Classifier: Programming Language :: Python :: Implementation :: PyPy
Classifier: Operating System :: OS Independent
License-File: LICENSE.txt
Requires-Dist: ecmwflibs>=0.5.3
Requires-Dist: netCDF4
Requires-Dist: dask[array]
Requires-Dist: Magics
Requires-Dist: Flask
Requires-Dist: xarray
Requires-Dist: geojson
Requires-Dist: future-annotations
Requires-Dist: python-dateutil
Requires-Dist: flask-cors
Dynamic: author
Dynamic: author-email
Dynamic: classifier
Dynamic: description
Dynamic: description-content-type
Dynamic: home-page
Dynamic: keywords
Dynamic: license
Dynamic: license-file
Dynamic: requires-dist
Dynamic: summary
